{
  "title": "10 Decks in 10 Weeks: A Wild Pair (G/R)",
  "folder": "20070312_10_Decks_in_10_Weeks_A_Wild_Pair_GR",
  "slug": "mtgcom/daily/bb103",
  "date": "20070312",
  "author": "Ben Bleiweiss",
  "url": "https://web.archive.org/web/20090601202842/https://www.wizards.com/Magic/Magazine/Article.aspx?x=mtgcom/daily/bb103",
  "status": "OK",
  "notes": "Screenshot failed: Page.goto: net::ERR_TIMED_OUT at https://web.archive.org/web/20090601202842/https://www.wizards.com/Magic/Magazine/Article.aspx?x=mtgcom/daily/bb103\nCall log:\n  - navigating to \"https://web.archive.org/web/20090601202842/https://www.wizards.com/Magic/Magazine/Article.aspx?x=mtgcom/daily/bb103\", waiting until \"networkidle\"\n;"
}